numtypes/__init__.py
numtypes/array.py
numtypes/debug.py
numtypes/types.py
numtypes-0.5.1.dist-info/METADATA
numtypes-0.5.1.dist-info/WHEEL
numtypes-0.5.1.dist-info/licenses/LICENSE
numtypes-0.5.1.dist-info/RECORD
