Metadata-Version: 2.4
Name: numtypes
Version: 0.5.1
Summary: A small library providing utilities for better type hinting of NumPy arrays.
Project-URL: Homepage, https://gitlab.com/zurabm/numtypes
Project-URL: Bug Tracker, https://gitlab.com/zurabm/numtypes/issues
Project-URL: Documentation, https://gitlab.com/zurabm/numtypes/-/blob/master/README.md
Author-email: Zurab Mujirishvili <zurab.mujirishvili@fau.de>
License: MIT
License-File: LICENSE
Keywords: arrays,numpy,shape,type-hints,typing
Classifier: Development Status :: 3 - Alpha
Classifier: Intended Audience :: Developers
Classifier: License :: OSI Approved :: MIT License
Classifier: Programming Language :: Python :: 3
Classifier: Programming Language :: Python :: 3.13
Classifier: Topic :: Software Development :: Libraries :: Python Modules
Classifier: Typing :: Typed
Requires-Python: >=3.13
Requires-Dist: numpy>=2.2.6
